<?xml version="1.0" encoding="UTF-8" standalone="yes"?>
<addon id="script.python-wrapper" name="Python Wrapper" version="0.1" provider-name="Alexis BRENON">
    <requires>
        <import addon="xbmc.python" version="2.1.0"/>
    </requires>
    <extension point="xbmc.python.script" library="default.py">
    </extension>
    <extension point="xbmc.addon.metadata">
        <summary lang="en">Allow python xbmc api calls</summary>
        <description lang="en"></description>
        <language></language>
        <platform>all</platform>
        <license></license>
        <website></website>
        <email></email>
        <source></source>
    </extension>
</addon>
